[
  {
    "player":"Alex",
    "total_earned":2,
    "total_errors":6,
    "points_per_set":0.6666666667,
    "errors_per_set":2.0,
    "points_per_match":0.1666666667,
    "errors_per_match":0.5
  },
  {
    "player":"Ando",
    "total_earned":9,
    "total_errors":1,
    "points_per_set":3.0,
    "errors_per_set":0.3333333333,
    "points_per_match":2.25,
    "errors_per_match":0.25
  },
  {
    "player":"Bo",
    "total_earned":0,
    "total_errors":0,
    "points_per_set":0.0,
    "errors_per_set":0.0,
    "points_per_match":0.0,
    "errors_per_match":0.0
  },
  {
    "player":"Bosse",
    "total_earned":0,
    "total_errors":1,
    "points_per_set":0.0,
    "errors_per_set":0.3333333333,
    "points_per_match":0.0,
    "errors_per_match":0.1111111111
  },
  {
    "player":"Gustav",
    "total_earned":6,
    "total_errors":3,
    "points_per_set":2.0,
    "errors_per_set":1.0,
    "points_per_match":0.75,
    "errors_per_match":0.375
  },
  {
    "player":"Hjorth",
    "total_earned":14,
    "total_errors":3,
    "points_per_set":4.6666666667,
    "errors_per_set":1.0,
    "points_per_match":14.0,
    "errors_per_match":3.0
  },
  {
    "player":"Martin",
    "total_earned":13,
    "total_errors":10,
    "points_per_set":4.3333333333,
    "errors_per_set":3.3333333333,
    "points_per_match":1.3,
    "errors_per_match":1.0
  },
  {
    "player":"Nicola",
    "total_earned":4,
    "total_errors":6,
    "points_per_set":1.3333333333,
    "errors_per_set":2.0,
    "points_per_match":0.3636363636,
    "errors_per_match":0.5454545455
  }
]